b_aws_cf_response/__init__.py
b_aws_cf_response/cfresponse.py
b_aws_cf_response_tests/unit/__init__.py
b_aws_cf_response_tests/unit/test_aws_cf_response.py
b_aws_cf_response-0.0.2.dist-info/LICENSE
b_aws_cf_response-0.0.2.dist-info/METADATA
b_aws_cf_response-0.0.2.dist-info/WHEEL
b_aws_cf_response-0.0.2.dist-info/top_level.txt
b_aws_cf_response-0.0.2.dist-info/RECORD
