Metadata-Version: 2.1
Name: b-aws-cf-response
Version: 0.0.2
Summary: Package makes a response message from a custom resource provider event and sends a callback to AWS CloudFormation service.
Home-page: https://github.com/Biomapas/B.AwsCfResponse.git
Author: Gediminas Kazlauskas
Author-email: gediminas.kazlauskas@biomapas.com
License: Apache License 2.0
Keywords: AWS CloudFormation Response Custom Resource
Platform: UNKNOWN
Classifier: Programming Language :: Python :: 3
Classifier: Operating System :: OS Independent
Requires-Dist: pytest (<7.0.0,>=6.2.5)
Requires-Dist: urllib3 (<2.0.0,>=1.26.6)
